README.rst
setup.py
Jasypt2Python.egg-info/PKG-INFO
Jasypt2Python.egg-info/SOURCES.txt
Jasypt2Python.egg-info/dependency_links.txt
Jasypt2Python.egg-info/requires.txt
Jasypt2Python.egg-info/top_level.txt
j2p/JASYPT.py
j2p/JASYPT_SHA256.py
j2p/__init__.py
tests/__init__.py
tests/test_jasypt_decryptor.py
tests/test_jasypt_encryptor.py