Metadata-Version: 1.0
Name: Jasypt2Python
Version: 1.0.1
Summary: Jasypt decryption library in Python
Home-page: https://github.com/TelmedIQ/jasypt-2-python
Author: Caleb Shortt
Author-email: caleb.shortt@telmediq.com
License: UNKNOWN
Keywords: jasypt,python,decryption
Platform: UNKNOWN
